CHANGES.txt
README.txt
bootstrap.py
buildout.cfg
pypi_upload.sh
setup.cfg
setup.py
test-plone-3.3.x.cfg
test-plone-4.0.x.cfg
collective/__init__.py
collective.portlet.recentactivity.egg-info/PKG-INFO
collective.portlet.recentactivity.egg-info/SOURCES.txt
collective.portlet.recentactivity.egg-info/dependency_links.txt
collective.portlet.recentactivity.egg-info/entry_points.txt
collective.portlet.recentactivity.egg-info/namespace_packages.txt
collective.portlet.recentactivity.egg-info/not-zip-safe
collective.portlet.recentactivity.egg-info/requires.txt
collective.portlet.recentactivity.egg-info/top_level.txt
collective/portlet/__init__.py
collective/portlet/recentactivity/__init__.py
collective/portlet/recentactivity/configure.zcml
collective/portlet/recentactivity/events.py
collective/portlet/recentactivity/interfaces.py
collective/portlet/recentactivity/portlet.pt
collective/portlet/recentactivity/portlet.py
collective/portlet/recentactivity/recentactivity.pt
collective/portlet/recentactivity/recentactivity.py
collective/portlet/recentactivity/subscribers.zcml
collective/portlet/recentactivity/update-translations.sh
collective/portlet/recentactivity/utilities.py
collective/portlet/recentactivity/utils.py
collective/portlet/recentactivity/viewlet.pt
collective/portlet/recentactivity/viewlet.py
collective/portlet/recentactivity/locales/collective.portlet.recentactivity.pot
collective/portlet/recentactivity/locales/extra.pot
collective/portlet/recentactivity/locales/ca/LC_MESSAGES/collective.portlet.recentactivity.po
collective/portlet/recentactivity/locales/de/LC_MESSAGES/collective.portlet.recentactivity.po
collective/portlet/recentactivity/locales/es/LC_MESSAGES/collective.portlet.recentactivity.po
collective/portlet/recentactivity/profiles/default/componentregistry.xml
collective/portlet/recentactivity/profiles/default/metadata.xml
collective/portlet/recentactivity/profiles/default/portlets.xml
collective/portlet/recentactivity/profiles/default/toolset.xml
collective/portlet/recentactivity/tests/__init__.py
collective/portlet/recentactivity/tests/base.py
collective/portlet/recentactivity/tests/test_portlet_recent_activity.py
collective/portlet/recentactivity/tests/test_utility.py
collective/portlet/recentactivity/tests/test_utils.py
collective/portlet/recentactivity/tests/test_viewlet.py
docs/INSTALL.txt
docs/LICENSE.GPL
docs/LICENSE.txt