Metadata-Version: 1.0
Name: collective.portlet.recentactivity
Version: 1.0b6
Summary: Recent activity portlet for Plone.
Home-page: http://svn.plone.org/svn/collective/collective.portlet.recentactivity
Author: Timo Stollenwerk
Author-email: timo@zmag.de
License: GPL
Platform: UNKNOWN
Classifier: Framework :: Plone
Classifier: Programming Language :: Python
